git_version_stamp.py
git_version_stamp-0.4.1.dist-info/METADATA
git_version_stamp-0.4.1.dist-info/WHEEL
git_version_stamp-0.4.1.dist-info/entry_points.txt
git_version_stamp-0.4.1.dist-info/RECORD
