Metadata-Version: 2.4
Name: git-version-stamp
Version: 0.4.1
Summary: Make a version from git repo/tree status for files of interest
Project-URL: Homepage, https://github.com/egnor/git-version-stamp/#readme
Project-URL: Repoository, https://github.com/egnor/git-version-stamp.git
Author-email: Dan Egnor <egnor@ofb.net>
Requires-Python: >=3.9
